i2bmi/__init__.py
i2bmi/utils.py
i2bmi-0.2.5.dist-info/LICENSE
i2bmi-0.2.5.dist-info/METADATA
i2bmi-0.2.5.dist-info/WHEEL
i2bmi-0.2.5.dist-info/top_level.txt
i2bmi-0.2.5.dist-info/RECORD
